too_short_url/__init__.py
too_short_url/__main__.py
too_short_url/check_url.py
too_short_url/too_st.py
too_short_url-0.1.0.dist-info/entry_points.txt
too_short_url-0.1.0.dist-info/WHEEL
too_short_url-0.1.0.dist-info/METADATA
too_short_url-0.1.0.dist-info/RECORD
