Metadata-Version: 2.1
Name: too-short-url
Version: 0.1.0
Summary: short url based on too.st
Home-page: https://github.com/ffreemt/too-short-url
License: MIT
Author: ffreemt
Requires-Python: >=3.8,<4.0
Classifier: License :: OSI Approved :: MIT License
Classifier: Programming Language :: Python :: 3
Classifier: Programming Language :: Python :: 3.10
Classifier: Programming Language :: Python :: 3.8
Classifier: Programming Language :: Python :: 3.9
Requires-Dist: Brotli (>=1.0.9,<2.0.0)
Requires-Dist: environs (>=9.5.0,<10.0.0)
Requires-Dist: furl (>=2.1.3,<3.0.0)
Requires-Dist: httpx (>=0.22.0,<0.23.0)
Requires-Dist: icecream (>=2.1.2,<3.0.0)
Requires-Dist: logzero (>=1.7.0,<2.0.0)
Requires-Dist: pyquery (>=1.4.3,<2.0.0)
Requires-Dist: typer (>=0.4.0,<0.5.0)
Requires-Dist: validators (>=0.18.2,<0.19.0)
Project-URL: Repository, https://github.com/ffreemt/too-short-url
